[
  {
    "id": 3051,
    "subject": "General Awareness",
    "chapter": "Core Essentials",
    "topic": "Global Tech Leaders",
    "difficulty": {
      "level": 3,
      "label": "basic",
      "scale": [
        "very_easy",
        "easy",
        "basic",
        "moderate",
        "intermediate",
        "hard",
        "very_hard"
      ]
    },
    "difficulty_weight": 0.35,
    "marks": 1,
    "negative_marks": 0,
    "question_type": "MCQ",
    "answer_type": "single_correct",
    "question_text": "Who is the current CEO of Alphabet Inc., the parent company of Google?",
    "options": [
      {
        "id": "A",
        "text": "Satya Nadella"
      },
      {
        "id": "B",
        "text": "Sundar Pichai"
      },
      {
        "id": "C",
        "text": "Andy Jassy"
      },
      {
        "id": "D",
        "text": "Mark Zuckerberg"
      }
    ],
    "correct_option": "B",
    "solution": {
      "final_answer": "Sundar Pichai",
      "explanation": {
        "concept": "Alphabet Inc. is the parent holding company of Google, and its CEO oversees multiple subsidiaries including Google.",
        "step_by_step": [
          "Identify the parent company of Google as Alphabet Inc.",
          "Recall the CEO associated with Alphabet.",
          "Match Sundar Pichai as CEO of both Google and Alphabet."
        ],
        "why_correct": {
          "B": "Sundar Pichai is the current CEO of Alphabet Inc."
        },
        "why_incorrect": {
          "A": "Satya Nadella is CEO of Microsoft.",
          "C": "Andy Jassy is CEO of Amazon.",
          "D": "Mark Zuckerberg leads Meta."
        }
      }
    },
    "question_state": "active",
    "variation_id": "VAR_3051",
    "confidence_score": 0.93,
    "metadata": {
      "estimated_time_sec": 30,
      "concepts": [
        "Corporate leadership"
      ],
      "formulae": []
    },
    "subtopic": "Core Essentials"
  },
  {
    "id": 3053,
    "subject": "General Awareness",
    "chapter": "Core Essentials",
    "topic": "Global Tech Leaders",
    "difficulty": {
      "level": 3,
      "label": "basic",
      "scale": [
        "very_easy",
        "easy",
        "basic",
        "moderate",
        "intermediate",
        "hard",
        "very_hard"
      ]
    },
    "difficulty_weight": 0.34,
    "marks": 1,
    "negative_marks": 0,
    "question_type": "MCQ",
    "answer_type": "single_correct",
    "question_text": "Who is the CEO of NVIDIA, a leading company in GPU and AI hardware development?",
    "options": [
      {
        "id": "A",
        "text": "Jensen Huang"
      },
      {
        "id": "B",
        "text": "Elon Musk"
      },
      {
        "id": "C",
        "text": "Lisa Su"
      },
      {
        "id": "D",
        "text": "Arvind Krishna"
      }
    ],
    "correct_option": "A",
    "solution": {
      "final_answer": "Jensen Huang",
      "explanation": {
        "concept": "NVIDIA is a key player in GPU and AI technology, led by its long-time CEO.",
        "step_by_step": [
          "Identify NVIDIA as an AI hardware company.",
          "Recall its founder-CEO.",
          "Recognize Jensen Huang as the CEO."
        ],
        "why_correct": {
          "A": "Jensen Huang is founder and CEO of NVIDIA."
        },
        "why_incorrect": {
          "B": "Elon Musk leads Tesla and SpaceX.",
          "C": "Lisa Su is CEO of AMD.",
          "D": "Arvind Krishna leads IBM."
        }
      }
    },
    "question_state": "active",
    "variation_id": "VAR_3053",
    "confidence_score": 0.94,
    "metadata": {
      "estimated_time_sec": 25,
      "concepts": [
        "AI industry leadership"
      ],
      "formulae": []
    },
    "subtopic": "Core Essentials"
  },
  {
    "id": 3058,
    "subject": "General Awareness",
    "chapter": "Core Essentials",
    "topic": "Global Tech Leaders",
    "difficulty": {
      "level": 3,
      "label": "basic",
      "scale": [
        "very_easy",
        "easy",
        "basic",
        "moderate",
        "intermediate",
        "hard",
        "very_hard"
      ]
    },
    "difficulty_weight": 0.33,
    "marks": 1,
    "negative_marks": 0,
    "question_type": "MCQ",
    "answer_type": "single_correct",
    "question_text": "Who is the CEO of Amazon after Jeff Bezos stepped down?",
    "options": [
      {
        "id": "A",
        "text": "Andy Jassy"
      },
      {
        "id": "B",
        "text": "Tim Cook"
      },
      {
        "id": "C",
        "text": "Satya Nadella"
      },
      {
        "id": "D",
        "text": "Sundar Pichai"
      }
    ],
    "correct_option": "A",
    "solution": {
      "final_answer": "Andy Jassy",
      "explanation": {
        "concept": "Amazon transitioned leadership from founder Jeff Bezos to a long-time executive.",
        "step_by_step": [
          "Recall Jeff Bezos stepped down.",
          "Identify successor.",
          "Select Andy Jassy."
        ],
        "why_correct": {
          "A": "Andy Jassy is CEO of Amazon."
        },
        "why_incorrect": {
          "B": "Tim Cook leads Apple.",
          "C": "Satya Nadella leads Microsoft.",
          "D": "Sundar Pichai leads Alphabet."
        }
      }
    },
    "question_state": "active",
    "variation_id": "VAR_3058",
    "confidence_score": 0.95,
    "metadata": {
      "estimated_time_sec": 25,
      "concepts": [
        "Corporate succession"
      ],
      "formulae": []
    },
    "subtopic": "Core Essentials"
  },
  {
    "id": 3061,
    "subject": "General Awareness",
    "chapter": "Core Essentials",
    "topic": "Global Tech Leaders",
    "difficulty": {
      "level": 4,
      "label": "moderate",
      "scale": [
        "very_easy",
        "easy",
        "basic",
        "moderate",
        "intermediate",
        "hard",
        "very_hard"
      ]
    },
    "difficulty_weight": 0.47,
    "marks": 1,
    "negative_marks": 0,
    "question_type": "MCQ",
    "answer_type": "single_correct",
    "question_text": "Who is the CEO of Microsoft, known for leading its transformation into a cloud-first company?",
    "options": [
      {
        "id": "A",
        "text": "Satya Nadella"
      },
      {
        "id": "B",
        "text": "Steve Ballmer"
      },
      {
        "id": "C",
        "text": "Tim Cook"
      },
      {
        "id": "D",
        "text": "Andy Jassy"
      }
    ],
    "correct_option": "A",
    "solution": {
      "final_answer": "Satya Nadella",
      "explanation": {
        "concept": "Microsoft’s shift toward cloud computing and AI has been driven under its current CEO.",
        "step_by_step": [
          "Identify Microsoft’s current CEO.",
          "Recall the leader responsible for Azure growth.",
          "Select Satya Nadella."
        ],
        "why_correct": {
          "A": "Satya Nadella is the CEO of Microsoft."
        },
        "why_incorrect": {
          "B": "Steve Ballmer is former CEO.",
          "C": "Tim Cook leads Apple.",
          "D": "Andy Jassy leads Amazon."
        }
      }
    },
    "question_state": "active",
    "variation_id": "VAR_3061",
    "confidence_score": 0.95,
    "metadata": {
      "estimated_time_sec": 30,
      "concepts": [
        "Cloud transformation"
      ],
      "formulae": []
    },
    "subtopic": "Core Essentials"
  },
  {
    "id": 3071,
    "subject": "General Awareness",
    "chapter": "Core Essentials",
    "topic": "Global Tech Leaders",
    "difficulty": {
      "level": 4,
      "label": "moderate",
      "scale": [
        "very_easy",
        "easy",
        "basic",
        "moderate",
        "intermediate",
        "hard",
        "very_hard"
      ]
    },
    "difficulty_weight": 0.48,
    "marks": 1,
    "negative_marks": 0,
    "question_type": "MCQ",
    "answer_type": "single_correct",
    "question_text": "Who is the CEO of Apple Inc., overseeing its global operations and product ecosystem?",
    "options": [
      {
        "id": "A",
        "text": "Tim Cook"
      },
      {
        "id": "B",
        "text": "Steve Jobs"
      },
      {
        "id": "C",
        "text": "Sundar Pichai"
      },
      {
        "id": "D",
        "text": "Satya Nadella"
      }
    ],
    "correct_option": "A",
    "solution": {
      "final_answer": "Tim Cook",
      "explanation": {
        "concept": "Apple’s leadership transitioned after Steve Jobs, with Tim Cook driving operational expansion.",
        "step_by_step": [
          "Identify Apple’s current CEO.",
          "Recall leadership post-Steve Jobs.",
          "Select Tim Cook."
        ],
        "why_correct": {
          "A": "Tim Cook is the current CEO of Apple."
        },
        "why_incorrect": {
          "B": "Steve Jobs was former CEO.",
          "C": "Pichai leads Alphabet.",
          "D": "Nadella leads Microsoft."
        }
      }
    },
    "question_state": "active",
    "variation_id": "VAR_3071",
    "confidence_score": 0.96,
    "metadata": {
      "estimated_time_sec": 25,
      "concepts": [
        "Global corporate leadership"
      ],
      "formulae": []
    },
    "subtopic": "Core Essentials"
  },
  {
    "id": 3075,
    "subject": "General Awareness",
    "chapter": "Core Essentials",
    "topic": "Global Tech Leaders",
    "difficulty": {
      "level": 6,
      "label": "hard",
      "scale": [
        "very_easy",
        "easy",
        "basic",
        "moderate",
        "intermediate",
        "hard",
        "very_hard"
      ]
    },
    "difficulty_weight": 0.63,
    "marks": 1,
    "negative_marks": 0,
    "question_type": "MCQ",
    "answer_type": "single_correct",
    "question_text": "Which CEO leads Meta Platforms, the parent company of Facebook, Instagram, and WhatsApp?",
    "options": [
      {
        "id": "A",
        "text": "Mark Zuckerberg"
      },
      {
        "id": "B",
        "text": "Elon Musk"
      },
      {
        "id": "C",
        "text": "Larry Page"
      },
      {
        "id": "D",
        "text": "Sergey Brin"
      }
    ],
    "correct_option": "A",
    "solution": {
      "final_answer": "Mark Zuckerberg",
      "explanation": {
        "concept": "Meta Platforms is led by its founder CEO who oversees major social media platforms.",
        "step_by_step": [
          "Identify Meta Platforms.",
          "Recall founder CEO.",
          "Select Mark Zuckerberg."
        ],
        "why_correct": {
          "A": "Mark Zuckerberg is CEO of Meta."
        },
        "why_incorrect": {
          "B": "Musk leads Tesla and X.",
          "C": "Page is co-founder of Google.",
          "D": "Brin is co-founder of Google."
        }
      }
    },
    "question_state": "active",
    "variation_id": "VAR_3075",
    "confidence_score": 0.96,
    "metadata": {
      "estimated_time_sec": 30,
      "concepts": [
        "Social media leadership"
      ],
      "formulae": []
    },
    "subtopic": "Core Essentials"
  },
  {
    "id": 3077,
    "subject": "General Awareness",
    "chapter": "Core Essentials",
    "topic": "Global Tech Leaders",
    "difficulty": {
      "level": 5,
      "label": "intermediate",
      "scale": [
        "very_easy",
        "easy",
        "basic",
        "moderate",
        "intermediate",
        "hard",
        "very_hard"
      ]
    },
    "difficulty_weight": 0.55,
    "marks": 1,
    "negative_marks": 0,
    "question_type": "MCQ",
    "answer_type": "single_correct",
    "question_text": "Who is the CEO of Tesla and also leads SpaceX and X (formerly Twitter)?",
    "options": [
      {
        "id": "A",
        "text": "Jeff Bezos"
      },
      {
        "id": "B",
        "text": "Elon Musk"
      },
      {
        "id": "C",
        "text": "Bill Gates"
      },
      {
        "id": "D",
        "text": "Larry Ellison"
      }
    ],
    "correct_option": "B",
    "solution": {
      "final_answer": "Elon Musk",
      "explanation": {
        "concept": "Some leaders head multiple influential companies across sectors.",
        "step_by_step": [
          "Identify Tesla leadership.",
          "Recall leader also associated with SpaceX and X.",
          "Select Elon Musk."
        ],
        "why_correct": {
          "B": "Elon Musk leads Tesla, SpaceX, and X."
        },
        "why_incorrect": {
          "A": "Bezos leads Blue Origin and Amazon (former CEO).",
          "C": "Gates is Microsoft co-founder.",
          "D": "Ellison is Oracle co-founder."
        }
      }
    },
    "question_state": "active",
    "variation_id": "VAR_3077",
    "confidence_score": 0.96,
    "metadata": {
      "estimated_time_sec": 30,
      "concepts": [
        "Multi-company leadership"
      ],
      "formulae": []
    },
    "subtopic": "Core Essentials"
  }
]