[
  {
    "id": 1500,
    "subject": "Logical Reasoning",
    "chapter": "Core Essentials",
    "topic": "Analogies",
    "difficulty": {
      "level": 4,
      "label": "moderate",
      "scale": [
        "very_easy",
        "easy",
        "basic",
        "moderate",
        "intermediate",
        "hard",
        "very_hard"
      ]
    },
    "difficulty_weight": 0.58,
    "marks": 2,
    "negative_marks": 1,
    "question_type": "MCQ",
    "answer_type": "single_correct",
    "question_text": "Pencil : Write :: Knife : ?",
    "options": [
      {
        "id": "A",
        "text": "Cut"
      },
      {
        "id": "B",
        "text": "Sharp"
      },
      {
        "id": "C",
        "text": "Metal"
      },
      {
        "id": "D",
        "text": "Tool"
      }
    ],
    "correct_option": "A",
    "solution": {
      "final_answer": "Cut",
      "explanation": {
        "concept": "Analogy based on function or purpose of an object.",
        "step_by_step": [
          "Pencil is used to write.",
          "Knife is used to cut.",
          "Thus relation is object → function."
        ],
        "why_correct": {
          "A": "Knife performs the function of cutting, similar to pencil used for writing."
        },
        "why_incorrect": {
          "B": "Sharp is a property, not the function.",
          "C": "Metal is material, not usage.",
          "D": "Tool is a category, not specific function."
        }
      }
    },
    "question_state": "active",
    "variation_id": "VAR_01",
    "confidence_score": 0.92,
    "metadata": {
      "estimated_time_sec": 45,
      "concepts": [
        "functional analogy"
      ],
      "formulae": []
    },
    "subtopic": "Core Essentials"
  },
  {
    "id": 1501,
    "subject": "Logical Reasoning",
    "chapter": "Core Essentials",
    "topic": "Analogies",
    "difficulty": {
      "level": 5,
      "label": "intermediate",
      "scale": [
        "very_easy",
        "easy",
        "basic",
        "moderate",
        "intermediate",
        "hard",
        "very_hard"
      ]
    },
    "difficulty_weight": 0.65,
    "marks": 2,
    "negative_marks": 1,
    "question_type": "MCQ",
    "answer_type": "single_correct",
    "question_text": "Seed : Tree :: Egg : ?",
    "options": [
      {
        "id": "A",
        "text": "Nest"
      },
      {
        "id": "B",
        "text": "Bird"
      },
      {
        "id": "C",
        "text": "Shell"
      },
      {
        "id": "D",
        "text": "Feather"
      }
    ],
    "correct_option": "B",
    "solution": {
      "final_answer": "Bird",
      "explanation": {
        "concept": "Analogy based on developmental stages.",
        "step_by_step": [
          "Seed grows into a tree.",
          "Egg develops into a bird.",
          "Thus relation is initial stage → final form."
        ],
        "why_correct": {
          "B": "Egg transforms into a bird, similar to seed becoming a tree."
        },
        "why_incorrect": {
          "A": "Nest is not a developmental outcome.",
          "C": "Shell is part of egg, not result.",
          "D": "Feather is a component, not complete organism."
        }
      }
    },
    "question_state": "active",
    "variation_id": "VAR_02",
    "confidence_score": 0.91,
    "metadata": {
      "estimated_time_sec": 50,
      "concepts": [
        "development analogy"
      ],
      "formulae": []
    },
    "subtopic": "Core Essentials"
  },
  {
    "id": 1502,
    "subject": "Logical Reasoning",
    "chapter": "Core Essentials",
    "topic": "Analogies",
    "difficulty": {
      "level": 6,
      "label": "hard",
      "scale": [
        "very_easy",
        "easy",
        "basic",
        "moderate",
        "intermediate",
        "hard",
        "very_hard"
      ]
    },
    "difficulty_weight": 0.72,
    "marks": 2,
    "negative_marks": 1,
    "question_type": "MCQ",
    "answer_type": "single_correct",
    "question_text": "Book : Author :: Painting : ?",
    "options": [
      {
        "id": "A",
        "text": "Brush"
      },
      {
        "id": "B",
        "text": "Canvas"
      },
      {
        "id": "C",
        "text": "Painter"
      },
      {
        "id": "D",
        "text": "Gallery"
      }
    ],
    "correct_option": "C",
    "solution": {
      "final_answer": "Painter",
      "explanation": {
        "concept": "Creator-product relationship.",
        "step_by_step": [
          "A book is created by an author.",
          "A painting is created by a painter.",
          "Thus relation is product → creator."
        ],
        "why_correct": {
          "C": "Painter creates painting, just like author writes book."
        },
        "why_incorrect": {
          "A": "Brush is a tool.",
          "B": "Canvas is medium.",
          "D": "Gallery is place of display."
        }
      }
    },
    "question_state": "active",
    "variation_id": "VAR_03",
    "confidence_score": 0.94,
    "metadata": {
      "estimated_time_sec": 55,
      "concepts": [
        "creator-product analogy"
      ],
      "formulae": []
    },
    "subtopic": "Core Essentials"
  },
  {
    "id": 1503,
    "subject": "Logical Reasoning",
    "chapter": "Core Essentials",
    "topic": "Analogies",
    "difficulty": {
      "level": 5,
      "label": "intermediate",
      "scale": [
        "very_easy",
        "easy",
        "basic",
        "moderate",
        "intermediate",
        "hard",
        "very_hard"
      ]
    },
    "difficulty_weight": 0.66,
    "marks": 2,
    "negative_marks": 1,
    "question_type": "MCQ",
    "answer_type": "single_correct",
    "question_text": "Clock : Time :: Thermometer : ?",
    "options": [
      {
        "id": "A",
        "text": "Heat"
      },
      {
        "id": "B",
        "text": "Temperature"
      },
      {
        "id": "C",
        "text": "Weather"
      },
      {
        "id": "D",
        "text": "Degree"
      }
    ],
    "correct_option": "B",
    "solution": {
      "final_answer": "Temperature",
      "explanation": {
        "concept": "Instrument and what it measures.",
        "step_by_step": [
          "Clock measures time.",
          "Thermometer measures temperature.",
          "Relation: instrument → measurement."
        ],
        "why_correct": {
          "B": "Thermometer directly measures temperature."
        },
        "why_incorrect": {
          "A": "Heat is vague concept.",
          "C": "Weather is broad.",
          "D": "Degree is unit, not measured quantity."
        }
      }
    },
    "question_state": "active",
    "variation_id": "VAR_04",
    "confidence_score": 0.93,
    "metadata": {
      "estimated_time_sec": 50,
      "concepts": [
        "measurement analogy"
      ],
      "formulae": []
    },
    "subtopic": "Core Essentials"
  },
  {
    "id": 1504,
    "subject": "Logical Reasoning",
    "chapter": "Core Essentials",
    "topic": "Analogies",
    "difficulty": {
      "level": 6,
      "label": "hard",
      "scale": [
        "very_easy",
        "easy",
        "basic",
        "moderate",
        "intermediate",
        "hard",
        "very_hard"
      ]
    },
    "difficulty_weight": 0.7,
    "marks": 2,
    "negative_marks": 1,
    "question_type": "MCQ",
    "answer_type": "single_correct",
    "question_text": "Teacher : School :: Doctor : ?",
    "options": [
      {
        "id": "A",
        "text": "Patient"
      },
      {
        "id": "B",
        "text": "Hospital"
      },
      {
        "id": "C",
        "text": "Medicine"
      },
      {
        "id": "D",
        "text": "Nurse"
      }
    ],
    "correct_option": "B",
    "solution": {
      "final_answer": "Hospital",
      "explanation": {
        "concept": "Profession and workplace relationship.",
        "step_by_step": [
          "Teacher works in a school.",
          "Doctor works in a hospital.",
          "Thus relation is profession → workplace."
        ],
        "why_correct": {
          "B": "Doctor works in hospital similar to teacher in school."
        },
        "why_incorrect": {
          "A": "Patient is recipient, not workplace.",
          "C": "Medicine is tool.",
          "D": "Nurse is colleague."
        }
      }
    },
    "question_state": "active",
    "variation_id": "VAR_05",
    "confidence_score": 0.92,
    "metadata": {
      "estimated_time_sec": 55,
      "concepts": [
        "profession analogy"
      ],
      "formulae": []
    },
    "subtopic": "Core Essentials"
  },
  {
    "id": 1505,
    "subject": "Logical Reasoning",
    "chapter": "Core Essentials",
    "topic": "Analogies",
    "difficulty": {
      "level": 7,
      "label": "very_hard",
      "scale": [
        "very_easy",
        "easy",
        "basic",
        "moderate",
        "intermediate",
        "hard",
        "very_hard"
      ]
    },
    "difficulty_weight": 0.82,
    "marks": 2,
    "negative_marks": 1,
    "question_type": "MCQ",
    "answer_type": "single_correct",
    "question_text": "Odometer : Distance :: Barometer : ?",
    "options": [
      {
        "id": "A",
        "text": "Air"
      },
      {
        "id": "B",
        "text": "Pressure"
      },
      {
        "id": "C",
        "text": "Weather"
      },
      {
        "id": "D",
        "text": "Wind"
      }
    ],
    "correct_option": "B",
    "solution": {
      "final_answer": "Pressure",
      "explanation": {
        "concept": "Scientific instrument analogy.",
        "step_by_step": [
          "Odometer measures distance.",
          "Barometer measures atmospheric pressure.",
          "Relation: device → quantity measured."
        ],
        "why_correct": {
          "B": "Barometer measures pressure."
        },
        "why_incorrect": {
          "A": "Air is medium.",
          "C": "Weather is broad outcome.",
          "D": "Wind is different measurement."
        }
      }
    },
    "question_state": "active",
    "variation_id": "VAR_06",
    "confidence_score": 0.9,
    "metadata": {
      "estimated_time_sec": 60,
      "concepts": [
        "scientific analogy"
      ],
      "formulae": []
    },
    "subtopic": "Core Essentials"
  },
  {
    "id": 1506,
    "subject": "Logical Reasoning",
    "chapter": "Core Essentials",
    "topic": "Analogies",
    "difficulty": {
      "level": 5,
      "label": "intermediate",
      "scale": [
        "very_easy",
        "easy",
        "basic",
        "moderate",
        "intermediate",
        "hard",
        "very_hard"
      ]
    },
    "difficulty_weight": 0.64,
    "marks": 2,
    "negative_marks": 1,
    "question_type": "MCQ",
    "answer_type": "single_correct",
    "question_text": "Fish : Water :: Bird : ?",
    "options": [
      {
        "id": "A",
        "text": "Tree"
      },
      {
        "id": "B",
        "text": "Sky"
      },
      {
        "id": "C",
        "text": "Nest"
      },
      {
        "id": "D",
        "text": "Air"
      }
    ],
    "correct_option": "D",
    "solution": {
      "final_answer": "Air",
      "explanation": {
        "concept": "Habitat/environment analogy.",
        "step_by_step": [
          "Fish lives in water.",
          "Bird lives in air.",
          "Relation is organism → natural environment."
        ],
        "why_correct": {
          "D": "Air is the medium bird moves in."
        },
        "why_incorrect": {
          "A": "Tree is optional habitat.",
          "B": "Sky is vague visual term.",
          "C": "Nest is temporary shelter."
        }
      }
    },
    "question_state": "active",
    "variation_id": "VAR_07",
    "confidence_score": 0.91,
    "metadata": {
      "estimated_time_sec": 45,
      "concepts": [
        "environment analogy"
      ],
      "formulae": []
    },
    "subtopic": "Core Essentials"
  },
  {
    "id": 1507,
    "subject": "Logical Reasoning",
    "chapter": "Core Essentials",
    "topic": "Analogies",
    "difficulty": {
      "level": 6,
      "label": "hard",
      "scale": [
        "very_easy",
        "easy",
        "basic",
        "moderate",
        "intermediate",
        "hard",
        "very_hard"
      ]
    },
    "difficulty_weight": 0.71,
    "marks": 2,
    "negative_marks": 1,
    "question_type": "MCQ",
    "answer_type": "single_correct",
    "question_text": "Key : Lock :: Password : ?",
    "options": [
      {
        "id": "A",
        "text": "Computer"
      },
      {
        "id": "B",
        "text": "Security"
      },
      {
        "id": "C",
        "text": "Account"
      },
      {
        "id": "D",
        "text": "Login"
      }
    ],
    "correct_option": "C",
    "solution": {
      "final_answer": "Account",
      "explanation": {
        "concept": "Access control analogy.",
        "step_by_step": [
          "Key opens lock.",
          "Password provides access to account.",
          "Relation: access tool → secured entity."
        ],
        "why_correct": {
          "C": "Password grants access to account."
        },
        "why_incorrect": {
          "A": "Computer is broad system.",
          "B": "Security is abstract.",
          "D": "Login is process, not entity."
        }
      }
    },
    "question_state": "active",
    "variation_id": "VAR_08",
    "confidence_score": 0.9,
    "metadata": {
      "estimated_time_sec": 60,
      "concepts": [
        "access analogy"
      ],
      "formulae": []
    },
    "subtopic": "Core Essentials"
  },
  {
    "id": 1508,
    "subject": "Logical Reasoning",
    "chapter": "Core Essentials",
    "topic": "Analogies",
    "difficulty": {
      "level": 4,
      "label": "moderate",
      "scale": [
        "very_easy",
        "easy",
        "basic",
        "moderate",
        "intermediate",
        "hard",
        "very_hard"
      ]
    },
    "difficulty_weight": 0.57,
    "marks": 2,
    "negative_marks": 1,
    "question_type": "MCQ",
    "answer_type": "single_correct",
    "question_text": "Leaf : Tree :: Petal : ?",
    "options": [
      {
        "id": "A",
        "text": "Flower"
      },
      {
        "id": "B",
        "text": "Plant"
      },
      {
        "id": "C",
        "text": "Stem"
      },
      {
        "id": "D",
        "text": "Root"
      }
    ],
    "correct_option": "A",
    "solution": {
      "final_answer": "Flower",
      "explanation": {
        "concept": "Part-whole relationship.",
        "step_by_step": [
          "Leaf is part of tree.",
          "Petal is part of flower.",
          "Relation is component → whole."
        ],
        "why_correct": {
          "A": "Petal belongs to flower."
        },
        "why_incorrect": {
          "B": "Plant is broader category.",
          "C": "Stem is different part.",
          "D": "Root unrelated."
        }
      }
    },
    "question_state": "active",
    "variation_id": "VAR_09",
    "confidence_score": 0.93,
    "metadata": {
      "estimated_time_sec": 45,
      "concepts": [
        "part-whole analogy"
      ],
      "formulae": []
    },
    "subtopic": "Core Essentials"
  },
  {
    "id": 1509,
    "subject": "Logical Reasoning",
    "chapter": "Core Essentials",
    "topic": "Analogies",
    "difficulty": {
      "level": 7,
      "label": "very_hard",
      "scale": [
        "very_easy",
        "easy",
        "basic",
        "moderate",
        "intermediate",
        "hard",
        "very_hard"
      ]
    },
    "difficulty_weight": 0.84,
    "marks": 2,
    "negative_marks": 1,
    "question_type": "MCQ",
    "answer_type": "single_correct",
    "question_text": "Justice : Court :: Cure : ?",
    "options": [
      {
        "id": "A",
        "text": "Doctor"
      },
      {
        "id": "B",
        "text": "Hospital"
      },
      {
        "id": "C",
        "text": "Medicine"
      },
      {
        "id": "D",
        "text": "Treatment"
      }
    ],
    "correct_option": "B",
    "solution": {
      "final_answer": "Hospital",
      "explanation": {
        "concept": "Outcome-place association analogy.",
        "step_by_step": [
          "Justice is delivered in court.",
          "Cure is achieved in hospital.",
          "Relation: result → place where achieved."
        ],
        "why_correct": {
          "B": "Hospital is place where cure is provided."
        },
        "why_incorrect": {
          "A": "Doctor is person, not place.",
          "C": "Medicine is means.",
          "D": "Treatment is process."
        }
      }
    },
    "question_state": "active",
    "variation_id": "VAR_10",
    "confidence_score": 0.89,
    "metadata": {
      "estimated_time_sec": 65,
      "concepts": [
        "place-outcome analogy"
      ],
      "formulae": []
    },
    "subtopic": "Core Essentials"
  }
]