[
  {
    "id": 8201,
    "subject": "Logical Reasoning",
    "topic": "Venn Diagrams",
    "difficulty": { "level": 3, "label": "basic" },
    "question_text": "Which of the following diagrams indicates the best relation between Travelers, Train, and Bus?",
    "options": [
      { "id": "A", "text": "Three separate circles" },
      { "id": "B", "text": "Two circles inside a larger circle" },
      { "id": "C", "text": "A circle with two other circles intersecting it but not each other" },
      { "id": "D", "text": "Three concentric circles" }
    ],
    "correct_option": "C",
    "solution": {
      "final_answer": "A circle with two other circles intersecting it but not each other",
      "explanation": {
        "concept": "Overlapping Categories",
        "step_by_step": [
          "Travelers can travel by Train, Bus, or both, or neither.",
          "Train and Bus are separate modes of transport (no overlap)."
        ]
      }
    },
    "question_state": "active"
  },
  {
    "id": 8202,
    "subject": "Logical Reasoning",
    "topic": "Venn Diagrams",
    "difficulty": { "level": 4, "label": "moderate" },
    "question_text": "In a Venn diagram representing 'Humans', 'Doctors', and 'Architects', how should they be placed?",
    "options": [
      { "id": "A", "text": "Three separate circles" },
      { "id": "B", "text": "Two separate circles inside one large circle" },
      { "id": "C", "text": "Two overlapping circles inside one large circle" },
      { "id": "D", "text": "Three intersecting circles" }
    ],
    "correct_option": "B",
    "solution": {
      "final_answer": "Two separate circles inside one large circle",
      "explanation": {
        "concept": "Subsets",
        "step_by_step": [
          "Both Doctors and Architects are Humans (inside the larger circle).",
          "Normally, a person is either a Doctor or an Architect (two separate roles)."
        ]
      }
    },
    "question_state": "active"
  },
  {
    "id": 8203,
    "subject": "Logical Reasoning",
    "topic": "Venn Diagrams",
    "difficulty": { "level": 4, "label": "moderate" },
    "question_text": "Identify the diagram that best represents the relationship among: 'Professors', 'Authors', and 'Infants'.",
    "options": [
      { "id": "A", "text": "Three intersecting circles" },
      { "id": "B", "text": "Two overlapping circles and one separate circle" },
      { "id": "C", "text": "Three separate circles" },
      { "id": "D", "text": "One circle inside another and one separate" }
    ],
    "correct_option": "B",
    "solution": {
      "final_answer": "Two overlapping circles and one separate circle",
      "explanation": {
        "concept": "Partial Overlap",
        "step_by_step": [
          "A Professor can be an Author and vice versa.",
          "An Infant cannot be a Professor or an Author (physically/socially impossible)."
        ]
      }
    },
    "question_state": "active"
  },
  {
    "id": 8204,
    "subject": "Logical Reasoning",
    "topic": "Venn Diagrams",
    "difficulty": { "level": 3, "label": "basic" },
    "question_text": "Which diagram represents 'Fruit', 'Apple', and 'Orange'?",
    "options": [
      { "id": "A", "text": "Two separate circles inside a larger one" },
      { "id": "B", "text": "Three concentric circles" },
      { "id": "C", "text": "Three overlapping circles" },
      { "id": "D", "text": "One circle inside another inside another" }
    ],
    "correct_option": "A",
    "solution": {
      "final_answer": "Two separate circles inside a larger one",
      "explanation": {
        "concept": "Hierarchical Logic",
        "step_by_step": [
          "Apple and Orange are both types of Fruit.",
          "An Apple is not an Orange."
        ]
      }
    },
    "question_state": "active"
  },
  {
    "id": 8205,
    "subject": "Logical Reasoning",
    "topic": "Venn Diagrams",
    "difficulty": { "level": 5, "label": "hard" },
    "question_text": "In a group of 50 people, 30 like tea, 25 like coffee, and 10 like both. How many like neither?",
    "options": [
      { "id": "A", "text": "5" },
      { "id": "B", "text": "10" },
      { "id": "C", "text": "15" },
      { "id": "D", "text": "0" }
    ],
    "correct_option": "A",
    "solution": {
      "final_answer": "5",
      "explanation": {
        "concept": "Quantitative Venn Diagram",
        "step_by_step": [
          "People liking Tea only = 30 - 10 = 20",
          "People liking Coffee only = 25 - 10 = 15",
          "Total liking either = 20 + 15 + 10 = 45",
          "Neither = 50 - 45 = 5"
        ]
      }
    },
    "question_state": "active"
  },
  {
    "id": 8206,
    "subject": "Logical Reasoning",
    "topic": "Venn Diagrams",
    "difficulty": { "level": 4, "label": "moderate" },
    "question_text": "Relation between 'Elephants', 'Wolves', and 'Animals':",
    "options": [
      { "id": "A", "text": "One circle inside another and one separate" },
      { "id": "B", "text": "Two separate circles inside one larger circle" },
      { "id": "C", "text": "Three intersecting circles" },
      { "id": "D", "text": "Three concentric circles" }
    ],
    "correct_option": "B",
    "solution": {
      "final_answer": "Two separate circles inside one larger circle",
      "explanation": {
        "concept": "Classification",
        "step_by_step": [
          "Both are animals, but they are distinct species."
        ]
      }
    },
    "question_state": "active"
  },
  {
    "id": 8207,
    "subject": "Logical Reasoning",
    "topic": "Venn Diagrams",
    "difficulty": { "level": 4, "label": "moderate" },
    "question_text": "Relation between 'Women', 'Mothers', and 'Doctors':",
    "options": [
      { "id": "A", "text": "One circle inside another, with a third circle intersecting both" },
      { "id": "B", "text": "Three separate circles" },
      { "id": "C", "text": "Two circles inside a larger one" },
      { "id": "D", "text": "Three intersecting circles" }
    ],
    "correct_option": "A",
    "solution": {
      "final_answer": "One circle inside another, with a third circle intersecting both",
      "explanation": {
        "concept": "Complex Intersections",
        "step_by_step": [
          "All Mothers are Women (Circle within Circle).",
          "Some Women are Doctors, and some Mothers are Doctors (Third circle cuts through both)."
        ]
      }
    },
    "question_state": "active"
  },
  {
    "id": 8208,
    "subject": "Logical Reasoning",
    "topic": "Venn Diagrams",
    "difficulty": { "level": 3, "label": "basic" },
    "question_text": "Relationship among 'Engineers', 'Software Engineers', and 'Web Developers':",
    "options": [
      { "id": "A", "text": "Three concentric circles" },
      { "id": "B", "text": "One large circle with two overlapping circles inside" },
      { "id": "C", "text": "Three separate circles" },
      { "id": "D", "text": "Two concentric and one separate" }
    ],
    "correct_option": "B",
    "solution": {
      "final_answer": "One large circle with two overlapping circles inside",
      "explanation": {
        "concept": "Professional Sets",
        "step_by_step": [
          "Software Engineers and Web Developers are types of Engineers.",
          "Many Web Developers are also Software Engineers."
        ]
      }
    },
    "question_state": "active"
  },
  {
    "id": 8209,
    "subject": "Logical Reasoning",
    "topic": "Venn Diagrams",
    "difficulty": { "level": 5, "label": "hard" },
    "question_text": "In a survey, 60% people like Movies, 50% like Music, and 10% like neither. What % like both?",
    "options": [
      { "id": "A", "text": "10%" },
      { "id": "B", "text": "20%" },
      { "id": "C", "text": "30%" },
      { "id": "D", "text": "40%" }
    ],
    "correct_option": "B",
    "solution": {
      "final_answer": "20%",
      "explanation": {
        "concept": "Percentage Venn",
        "step_by_step": [
          "Total who like either = 100% - 10% = 90%",
          "P(A or B) = P(A) + P(B) - P(A and B)",
          "90 = 60 + 50 - X => X = 110 - 90 = 20"
        ]
      }
    },
    "question_state": "active"
  },
  {
    "id": 8210,
    "subject": "Logical Reasoning",
    "topic": "Venn Diagrams",
    "difficulty": { "level": 4, "label": "moderate" },
    "question_text": "Relation between 'States', 'Countries', and 'Districts':",
    "options": [
      { "id": "A", "text": "Three concentric circles" },
      { "id": "B", "text": "Three separate circles" },
      { "id": "C", "text": "Two circles inside one larger circle" },
      { "id": "D", "text": "Three intersecting circles" }
    ],
    "correct_option": "A",
    "solution": {
      "final_answer": "Three concentric circles",
      "explanation": {
        "concept": "Geographical Hierarchy",
        "step_by_step": [
          "Districts are within States, which are within Countries."
        ]
      }
    },
    "question_state": "active"
  }
]
