{
  "mock_id": "FULL-MOCK-19",
  "mock_type": "full_mock",
  "mock_number": 19,
  "total_questions": 50,
  "total_marks": 50,
  "duration_seconds": 2400,
  "negative_marking": false,
  "marks_per_correct": 1,
  "marks_per_wrong": 0,
  "sections": [
    {
      "section_id": "S1",
      "subject": "english",
      "total_questions": 30,
      "total_marks": 30,
      "questions": [
        "ENG-RC-023",
        "ENG-IDIOM-001",
        "ENG-SPEECH-010",
        "ENG-RC-032",
        "ENG-SPEECH-014",
        "ENG-VOICE-009",
        "ENG-IDIOM-006",
        "ENG-FIB-014",
        "ENG-VOICE-045",
        "ENG-TENSE-012",
        "ENG-IDIOM-004",
        "ENG-CLOZE-016",
        "ENG-SENTTYPE-003",
        "ENG-CLOZE-010",
        "ENG-IDIOM-009",
        "ENG-MODAL-001",
        "ENG-VOICE-043",
        "ENG-TENSE-024",
        "ENG-TENSE-053",
        "ENG-MODAL-036",
        "ENG-IDIOM-019",
        "ENG-VOICE-004",
        "ENG-VOICE-011",
        "ENG-TENSE-049",
        "ENG-CLOZE-025",
        "ENG-CONJ-023",
        "ENG-MODAL-024",
        "ENG-CLOZE-035",
        "ENG-SENTTYPE-030",
        "ENG-SENTCOR-040"
      ]
    },
    {
      "section_id": "S2",
      "subject": "reasoning",
      "total_questions": 20,
      "total_marks": 20,
      "questions": [
        "RSN-SYL-007",
        "RSN-PER-014",
        "RSN-COD-020",
        "RSN-PL-005",
        "RSN-SA-007",
        "RSN-DI-011",
        "RSN-ANA-018",
        "RSN-COD-024",
        "RSN-DI-001",
        "RSN-AVG-016",
        "RSN-NLS-024",
        "RSN-AVG-007",
        "RSN-ANA-045",
        "RSN-SA-027",
        "RSN-AGE-026",
        "RSN-BR-031",
        "RSN-COD-051",
        "RSN-DIR-018",
        "RSN-SYL-028",
        "RSN-DI-051"
      ]
    }
  ],
  "status": "not_started",
  "created_at": "2026-04-26T04:10:10.906966+00:00"
}